<GML>
    <tag>
        <header>
            <client>
                <name>Graffiti Analysis 2.0</name>
                <version>1.0</version>
                <username>dustTag</username>
                <keywords></keywords>
                <uniqueKey></uniqueKey>
            </client>
        </header>
        <drawing>
            <stroke>
                <pt>
                    <x>0.250781</x>
                    <y>0.478906</y>
                    <z>223.625183</z>
                    <time>0.000000</time>
                </pt>
                <pt>
                    <x>0.252539</x>
                    <y>0.477539</y>
                    <z>227.750061</z>
                    <time>0.065998</time>
                </pt>
                <pt>
                    <x>0.253760</x>
                    <y>0.475635</y>
                    <z>231.875183</z>
                    <time>0.132000</time>
                </pt>
                <pt>
                    <x>0.257971</x>
                    <y>0.474377</y>
                    <z>240.250107</z>
                    <time>0.265999</time>
                </pt>
                <pt>
                    <x>0.268399</x>
                    <y>0.470938</y>
                    <z>244.437698</z>
                    <time>0.333000</time>
                </pt>
                <pt>
                    <x>0.282725</x>
                    <y>0.464610</y>
                    <z>248.625046</z>
                    <time>0.399998</time>
                </pt>
                <pt>
                    <x>0.290994</x>
                    <y>0.453652</y>
                    <z>252.812622</z>
                    <time>0.466999</time>
                </pt>
                <pt>
                    <x>0.292280</x>
                    <y>0.438413</y>
                    <z>257.062683</z>
                    <time>0.535000</time>
                </pt>
                <pt>
                    <x>0.288695</x>
                    <y>0.426791</y>
                    <z>261.250031</z>
                    <time>0.601997</time>
                </pt>
                <pt>
                    <x>0.277642</x>
                    <y>0.420760</y>
                    <z>265.437592</z>
                    <time>0.668999</time>
                </pt>
                <pt>
                    <x>0.260817</x>
                    <y>0.422378</y>
                    <z>268.750183</z>
                    <time>0.722000</time>
                </pt>
                <pt>
                    <x>0.248017</x>
                    <y>0.432157</y>
                    <z>273.812531</z>
                    <time>0.802998</time>
                </pt>
                <pt>
                    <x>0.240129</x>
                    <y>0.444758</y>
                    <z>278.000122</z>
                    <time>0.869999</time>
                </pt>
                <pt>
                    <x>0.238157</x>
                    <y>0.458064</y>
                    <z>282.125244</z>
                    <time>0.936001</time>
                </pt>
                <pt>
                    <x>0.239227</x>
                    <y>0.466860</y>
                    <z>286.375061</z>
                    <time>1.003998</time>
                </pt>
                <pt>
                    <x>0.244182</x>
                    <y>0.469840</y>
                    <z>290.562622</z>
                    <time>1.070999</time>
                </pt>
                <pt>
                    <x>0.250889</x>
                    <y>0.468241</y>
                    <z>294.687500</z>
                    <time>1.136997</time>
                </pt>
                <pt>
                    <x>0.263504</x>
                    <y>0.466279</y>
                    <z>298.000092</z>
                    <time>1.189999</time>
                </pt>
                <pt>
                    <x>0.283845</x>
                    <y>0.465789</y>
                    <z>302.000061</z>
                    <time>1.253998</time>
                </pt>
                <pt>
                    <x>0.302992</x>
                    <y>0.465666</y>
                    <z>306.250092</z>
                    <time>1.321999</time>
                </pt>
                <pt>
                    <x>0.321842</x>
                    <y>0.465635</y>
                    <z>310.687531</z>
                    <time>1.392998</time>
                </pt>
                <pt>
                    <x>0.339835</x>
                    <y>0.464846</y>
                    <z>314.625031</z>
                    <time>1.455997</time>
                </pt>
                <pt>
                    <x>0.356053</x>
                    <y>0.462305</y>
                    <z>318.750153</z>
                    <time>1.521999</time>
                </pt>
                <pt>
                    <x>0.372607</x>
                    <y>0.460889</y>
                    <z>322.937714</z>
                    <time>1.589001</time>
                </pt>
                <pt>
                    <x>0.390808</x>
                    <y>0.462097</y>
                    <z>326.187622</z>
                    <time>1.640999</time>
                </pt>
                <pt>
                    <x>0.410202</x>
                    <y>0.463181</y>
                    <z>330.375183</z>
                    <time>1.708000</time>
                </pt>
                <pt>
                    <x>0.431457</x>
                    <y>0.464233</y>
                    <z>336.625092</z>
                    <time>1.807999</time>
                </pt>
                <pt>
                    <x>0.453177</x>
                    <y>0.462152</y>
                    <z>340.812683</z>
                    <time>1.875000</time>
                </pt>
                <pt>
                    <x>0.475794</x>
                    <y>0.460069</y>
                    <z>345.062744</z>
                    <time>1.943001</time>
                </pt>
                <pt>
                    <x>0.498636</x>
                    <y>0.459549</y>
                    <z>349.250092</z>
                    <time>2.009998</time>
                </pt>
                <pt>
                    <x>0.518409</x>
                    <y>0.459418</y>
                    <z>353.437653</z>
                    <time>2.077000</time>
                </pt>
                <pt>
                    <x>0.536633</x>
                    <y>0.459386</y>
                    <z>357.687714</z>
                    <time>2.145000</time>
                </pt>
                <pt>
                    <x>0.551346</x>
                    <y>0.457034</y>
                    <z>362.000214</z>
                    <time>2.214001</time>
                </pt>
                <pt>
                    <x>0.560493</x>
                    <y>0.449415</y>
                    <z>366.250031</z>
                    <time>2.281998</time>
                </pt>
                <pt>
                    <x>0.561998</x>
                    <y>0.439697</y>
                    <z>371.125214</z>
                    <time>2.360001</time>
                </pt>
                <pt>
                    <x>0.553781</x>
                    <y>0.430237</y>
                    <z>374.312653</z>
                    <time>2.410999</time>
                </pt>
                <pt>
                    <x>0.538445</x>
                    <y>0.425528</y>
                    <z>378.437531</z>
                    <time>2.476997</time>
                </pt>
                <pt>
                    <x>0.517424</x>
                    <y>0.423570</y>
                    <z>382.500183</z>
                    <time>2.542000</time>
                </pt>
                <pt>
                    <x>0.495762</x>
                    <y>0.426986</y>
                    <z>386.750214</z>
                    <time>2.610001</time>
                </pt>
                <pt>
                    <x>0.480191</x>
                    <y>0.434872</y>
                    <z>390.000092</z>
                    <time>2.661999</time>
                </pt>
                <pt>
                    <x>0.472391</x>
                    <y>0.443093</y>
                    <z>395.062683</z>
                    <time>2.743000</time>
                </pt>
                <pt>
                    <x>0.475129</x>
                    <y>0.448273</y>
                    <z>398.375031</z>
                    <time>2.795998</time>
                </pt>
                <pt>
                    <x>0.485970</x>
                    <y>0.449568</y>
                    <z>402.562622</z>
                    <time>2.862999</time>
                </pt>
                <pt>
                    <x>0.501961</x>
                    <y>0.449111</y>
                    <z>406.812683</z>
                    <time>2.931000</time>
                </pt>
                <pt>
                    <x>0.522365</x>
                    <y>0.446653</y>
                    <z>410.937561</z>
                    <time>2.996998</time>
                </pt>
                <pt>
                    <x>0.544654</x>
                    <y>0.444476</y>
                    <z>415.125122</z>
                    <time>3.063999</time>
                </pt>
                <pt>
                    <x>0.568976</x>
                    <y>0.443931</y>
                    <z>419.312714</z>
                    <time>3.131001</time>
                </pt>
                <pt>
                    <x>0.593025</x>
                    <y>0.444577</y>
                    <z>423.562531</z>
                    <time>3.198997</time>
                </pt>
                <pt>
                    <x>0.615444</x>
                    <y>0.447082</y>
                    <z>427.750122</z>
                    <time>3.265999</time>
                </pt>
                <pt>
                    <x>0.638236</x>
                    <y>0.449270</y>
                    <z>431.875244</z>
                    <time>3.332001</time>
                </pt>
                <pt>
                    <x>0.661903</x>
                    <y>0.447474</y>
                    <z>435.937653</z>
                    <time>3.396999</time>
                </pt>
                <pt>
                    <x>0.682663</x>
                    <y>0.438431</y>
                    <z>440.250153</z>
                    <time>3.466000</time>
                </pt>
                <pt>
                    <x>0.698009</x>
                    <y>0.422889</y>
                    <z>444.250122</z>
                    <time>3.529999</time>
                </pt>
                <pt>
                    <x>0.704971</x>
                    <y>0.403378</y>
                    <z>448.750031</z>
                    <time>3.601997</time>
                </pt>
                <pt>
                    <x>0.701243</x>
                    <y>0.386782</y>
                    <z>452.875122</z>
                    <time>3.667999</time>
                </pt>
                <pt>
                    <x>0.692498</x>
                    <y>0.377946</y>
                    <z>456.875092</z>
                    <time>3.731998</time>
                </pt>
                <pt>
                    <x>0.680937</x>
                    <y>0.378861</y>
                    <z>461.062683</z>
                    <time>3.799000</time>
                </pt>
                <pt>
                    <x>0.669453</x>
                    <y>0.390028</y>
                    <z>465.187561</z>
                    <time>3.864998</time>
                </pt>
                <pt>
                    <x>0.661895</x>
                    <y>0.406882</y>
                    <z>468.562592</z>
                    <time>3.918999</time>
                </pt>
                <pt>
                    <x>0.662349</x>
                    <y>0.424377</y>
                    <z>473.687653</z>
                    <time>4.000999</time>
                </pt>
                <pt>
                    <x>0.669493</x>
                    <y>0.438125</y>
                    <z>479.937561</z>
                    <time>4.100998</time>
                </pt>
                <pt>
                    <x>0.679873</x>
                    <y>0.443906</y>
                    <z>484.125122</z>
                    <time>4.167999</time>
                </pt>
                <pt>
                    <x>0.694187</x>
                    <y>0.439102</y>
                    <z>488.312714</z>
                    <time>4.235001</time>
                </pt>
                <pt>
                    <x>0.707141</x>
                    <y>0.423057</y>
                    <z>491.750000</z>
                    <time>4.289997</time>
                </pt>
                <pt>
                    <x>0.712723</x>
                    <y>0.401858</y>
                    <z>496.750122</z>
                    <time>4.369999</time>
                </pt>
                <pt>
                    <x>0.708649</x>
                    <y>0.380152</y>
                    <z>500.812531</z>
                    <time>4.434998</time>
                </pt>
                <pt>
                    <x>0.694350</x>
                    <y>0.363788</y>
                    <z>505.062592</z>
                    <time>4.502998</time>
                </pt>
                <pt>
                    <x>0.672806</x>
                    <y>0.351884</y>
                    <z>509.187683</z>
                    <time>4.569000</time>
                </pt>
                <pt>
                    <x>0.644764</x>
                    <y>0.346565</y>
                    <z>512.625244</z>
                    <time>4.624001</time>
                </pt>
                <pt>
                    <x>0.611191</x>
                    <y>0.348360</y>
                    <z>516.750122</z>
                    <time>4.689999</time>
                </pt>
                <pt>
                    <x>0.575454</x>
                    <y>0.354277</y>
                    <z>520.812500</z>
                    <time>4.754997</time>
                </pt>
                <pt>
                    <x>0.539957</x>
                    <y>0.363569</y>
                    <z>525.937561</z>
                    <time>4.836998</time>
                </pt>
                <pt>
                    <x>0.503739</x>
                    <y>0.375267</y>
                    <z>529.125244</z>
                    <time>4.888000</time>
                </pt>
                <pt>
                    <x>0.469685</x>
                    <y>0.387567</y>
                    <z>532.375122</z>
                    <time>4.939999</time>
                </pt>
                <pt>
                    <x>0.437734</x>
                    <y>0.400017</y>
                    <z>537.437683</z>
                    <time>5.021000</time>
                </pt>
                <pt>
                    <x>0.406308</x>
                    <y>0.413285</y>
                    <z>540.687561</z>
                    <time>5.072998</time>
                </pt>
                <pt>
                    <x>0.376577</x>
                    <y>0.427540</y>
                    <z>544.875122</z>
                    <time>5.139999</time>
                </pt>
                <pt>
                    <x>0.351176</x>
                    <y>0.439698</y>
                    <z>549.062744</z>
                    <time>5.207001</time>
                </pt>
                <pt>
                    <x>0.327638</x>
                    <y>0.451331</y>
                    <z>553.250061</z>
                    <time>5.273998</time>
                </pt>
                <pt>
                    <x>0.303784</x>
                    <y>0.465176</y>
                    <z>557.437683</z>
                    <time>5.341000</time>
                </pt>
                <pt>
                    <x>0.282977</x>
                    <y>0.474888</y>
                    <z>561.625000</z>
                    <time>5.407997</time>
                </pt>
                <pt>
                    <x>0.266057</x>
                    <y>0.474972</y>
                    <z>565.812561</z>
                    <time>5.474998</time>
                </pt>
                <pt>
                    <x>0.252452</x>
                    <y>0.464837</y>
                    <z>570.000183</z>
                    <time>5.542000</time>
                </pt>
                <pt>
                    <x>0.245144</x>
                    <y>0.445115</y>
                    <z>574.187500</z>
                    <time>5.608997</time>
                </pt>
                <pt>
                    <x>0.241755</x>
                    <y>0.420654</y>
                    <z>578.375122</z>
                    <time>5.675999</time>
                </pt>
                <pt>
                    <x>0.241689</x>
                    <y>0.392663</y>
                    <z>583.500122</z>
                    <time>5.757999</time>
                </pt>
                <pt>
                    <x>0.244016</x>
                    <y>0.362228</y>
                    <z>587.812683</z>
                    <time>5.827000</time>
                </pt>
                <pt>
                    <x>0.246941</x>
                    <y>0.331182</y>
                    <z>590.937622</z>
                    <time>5.876999</time>
                </pt>
                <pt>
                    <x>0.252360</x>
                    <y>0.299983</y>
                    <z>595.000000</z>
                    <time>5.941998</time>
                </pt>
                <pt>
                    <x>0.263090</x>
                    <y>0.269527</y>
                    <z>599.125122</z>
                    <time>6.007999</time>
                </pt>
                <pt>
                    <x>0.275148</x>
                    <y>0.240819</y>
                    <z>603.312744</z>
                    <time>6.075001</time>
                </pt>
                <pt>
                    <x>0.287537</x>
                    <y>0.214111</y>
                    <z>607.562561</z>
                    <time>6.142998</time>
                </pt>
                <pt>
                    <x>0.301572</x>
                    <y>0.191028</y>
                    <z>610.812683</z>
                    <time>6.195000</time>
                </pt>
                <pt>
                    <x>0.319143</x>
                    <y>0.169632</y>
                    <z>615.000000</z>
                    <time>6.261997</time>
                </pt>
                <pt>
                    <x>0.337598</x>
                    <y>0.151783</y>
                    <z>621.250122</z>
                    <time>6.362000</time>
                </pt>
                <pt>
                    <x>0.357056</x>
                    <y>0.137946</y>
                    <z>625.437500</z>
                    <time>6.428997</time>
                </pt>
                <pt>
                    <x>0.378326</x>
                    <y>0.126674</y>
                    <z>629.750000</z>
                    <time>6.497997</time>
                </pt>
                <pt>
                    <x>0.400050</x>
                    <y>0.119168</y>
                    <z>633.812683</z>
                    <time>6.563000</time>
                </pt>
                <pt>
                    <x>0.422669</x>
                    <y>0.114167</y>
                    <z>638.062744</z>
                    <time>6.631001</time>
                </pt>
                <pt>
                    <x>0.445511</x>
                    <y>0.113698</y>
                    <z>642.187622</z>
                    <time>6.696999</time>
                </pt>
                <pt>
                    <x>0.465284</x>
                    <y>0.116706</y>
                    <z>646.375183</z>
                    <time>6.764000</time>
                </pt>
                <pt>
                    <x>0.483508</x>
                    <y>0.122145</y>
                    <z>650.562500</z>
                    <time>6.830997</time>
                </pt>
                <pt>
                    <x>0.500565</x>
                    <y>0.128193</y>
                    <z>654.625183</z>
                    <time>6.896000</time>
                </pt>
                <pt>
                    <x>0.518891</x>
                    <y>0.134392</y>
                    <z>658.812500</z>
                    <time>6.962997</time>
                </pt>
                <pt>
                    <x>0.537535</x>
                    <y>0.139848</y>
                    <z>663.000122</z>
                    <time>7.029999</time>
                </pt>
                <pt>
                    <x>0.556259</x>
                    <y>0.144337</y>
                    <z>667.187683</z>
                    <time>7.097000</time>
                </pt>
                <pt>
                    <x>0.575002</x>
                    <y>0.150147</y>
                    <z>671.375061</z>
                    <time>7.163998</time>
                </pt>
                <pt>
                    <x>0.593751</x>
                    <y>0.157068</y>
                    <z>675.562622</z>
                    <time>7.230999</time>
                </pt>
                <pt>
                    <x>0.611719</x>
                    <y>0.166611</y>
                    <z>679.687500</z>
                    <time>7.296997</time>
                </pt>
                <pt>
                    <x>0.627930</x>
                    <y>0.179153</y>
                    <z>683.062561</z>
                    <time>7.350998</time>
                </pt>
                <pt>
                    <x>0.642920</x>
                    <y>0.194788</y>
                    <z>687.250122</z>
                    <time>7.417999</time>
                </pt>
                <pt>
                    <x>0.656043</x>
                    <y>0.212760</y>
                    <z>692.250000</z>
                    <time>7.497997</time>
                </pt>
                <pt>
                    <x>0.668698</x>
                    <y>0.232096</y>
                    <z>696.437622</z>
                    <time>7.564999</time>
                </pt>
                <pt>
                    <x>0.680456</x>
                    <y>0.252555</y>
                    <z>701.812500</z>
                    <time>7.650997</time>
                </pt>
                <pt>
                    <x>0.689645</x>
                    <y>0.272514</y>
                    <z>703.937500</z>
                    <time>7.684998</time>
                </pt>
                <pt>
                    <x>0.695849</x>
                    <y>0.293910</y>
                    <z>708.250061</z>
                    <time>7.753998</time>
                </pt>
                <pt>
                    <x>0.699743</x>
                    <y>0.314884</y>
                    <z>713.312622</z>
                    <time>7.834999</time>
                </pt>
                <pt>
                    <x>0.703061</x>
                    <y>0.333408</y>
                    <z>716.562500</z>
                    <time>7.886997</time>
                </pt>
                <pt>
                    <x>0.705453</x>
                    <y>0.348977</y>
                    <z>721.625061</z>
                    <time>7.967999</time>
                </pt>
                <pt>
                    <x>0.706051</x>
                    <y>0.362244</y>
                    <z>725.812683</z>
                    <time>8.035000</time>
                </pt>
                <pt>
                    <x>0.706981</x>
                    <y>0.375717</y>
                    <z>729.250183</z>
                    <time>8.090000</time>
                </pt>
                <pt>
                    <x>0.708777</x>
                    <y>0.390804</y>
                    <z>733.250122</z>
                    <time>8.153999</time>
                </pt>
                <pt>
                    <x>0.709225</x>
                    <y>0.405514</y>
                    <z>737.312561</z>
                    <time>8.218998</time>
                </pt>
                <pt>
                    <x>0.709338</x>
                    <y>0.417785</y>
                    <z>741.437683</z>
                    <time>8.285000</time>
                </pt>
                <pt>
                    <x>0.706241</x>
                    <y>0.425540</y>
                    <z>745.625000</z>
                    <time>8.351997</time>
                </pt>
                <pt>
                    <x>0.695310</x>
                    <y>0.426697</y>
                    <z>749.937561</z>
                    <time>8.420998</time>
                </pt>
                <pt>
                    <x>0.681640</x>
                    <y>0.424643</y>
                    <z>753.062744</z>
                    <time>8.471001</time>
                </pt>
                <pt>
                    <x>0.671191</x>
                    <y>0.422567</y>
                    <z>759.437561</z>
                    <time>8.572998</time>
                </pt>
                <pt>
                    <x>0.668579</x>
                    <y>0.421267</y>
                    <z>763.625122</z>
                    <time>8.639999</time>
                </pt>
                <pt>
                    <x>0.671832</x>
                    <y>0.419379</y>
                    <z>767.750000</z>
                    <time>8.705997</time>
                </pt>
                <pt>
                    <x>0.674989</x>
                    <y>0.418907</y>
                    <z>772.000061</z>
                    <time>8.773998</time>
                </pt>
                <pt>
                    <x>0.676560</x>
                    <y>0.418008</y>
                    <z>776.187683</z>
                    <time>8.841000</time>
                </pt>
                <pt>
                    <x>0.669921</x>
                    <y>0.416221</y>
                    <z>780.312561</z>
                    <time>8.906998</time>
                </pt>
                <pt>
                    <x>0.651074</x>
                    <y>0.416555</y>
                    <z>784.500122</z>
                    <time>8.973999</time>
                </pt>
                <pt>
                    <x>0.626050</x>
                    <y>0.417420</y>
                    <z>788.750183</z>
                    <time>9.042000</time>
                </pt>
                <pt>
                    <x>0.594012</x>
                    <y>0.415293</y>
                    <z>792.812561</z>
                    <time>9.106998</time>
                </pt>
                <pt>
                    <x>0.553191</x>
                    <y>0.412417</y>
                    <z>797.000183</z>
                    <time>9.174000</time>
                </pt>
                <pt>
                    <x>0.504704</x>
                    <y>0.411698</y>
                    <z>801.062561</z>
                    <time>9.238998</time>
                </pt>
                <pt>
                    <x>0.451957</x>
                    <y>0.415424</y>
                    <z>805.312622</z>
                    <time>9.306999</time>
                </pt>
                <pt>
                    <x>0.398927</x>
                    <y>0.421044</y>
                    <z>809.500244</z>
                    <time>9.374001</time>
                </pt>
                <pt>
                    <x>0.352857</x>
                    <y>0.430261</y>
                    <z>813.687561</z>
                    <time>9.440998</time>
                </pt>
                <pt>
                    <x>0.315558</x>
                    <y>0.437253</y>
                    <z>817.875122</z>
                    <time>9.507999</time>
                </pt>
                <pt>
                    <x>0.287483</x>
                    <y>0.443688</y>
                    <z>822.062744</z>
                    <time>9.575001</time>
                </pt>
                <pt>
                    <x>0.268746</x>
                    <y>0.449985</y>
                    <z>825.312622</z>
                    <time>9.626999</time>
                </pt>
                <pt>
                    <x>0.260936</x>
                    <y>0.456246</y>
                    <z>830.375183</z>
                    <time>9.708000</time>
                </pt>
                <pt>
                    <x>0.263672</x>
                    <y>0.460937</y>
                    <z>833.687561</z>
                    <time>9.760998</time>
                </pt>
                <pt>
                    <x>0.267480</x>
                    <y>0.462890</y>
                    <z>837.937622</z>
                    <time>9.828999</time>
                </pt>
                <pt>
                    <x>0.266089</x>
                    <y>0.465723</y>
                    <z>842.062683</z>
                    <time>9.895000</time>
                </pt>
                <pt>
                    <x>0.259491</x>
                    <y>0.467212</y>
                    <z>850.437622</z>
                    <time>10.028999</time>
                </pt>
                <pt>
                    <x>0.256279</x>
                    <y>0.464459</y>
                    <z>854.562500</z>
                    <time>10.094997</time>
                </pt>
                <pt>
                    <x>0.206250</x>
                    <y>0.300000</y>
                    <z>918.625122</z>
                    <time>11.119999</time>
                </pt>
            </stroke>
        </drawing>
    </tag>
</GML>
